btrfs_simple_snapshots.py
btrfs_simple_snapshots-0.1.4.dist-info/DESCRIPTION.rst
btrfs_simple_snapshots-0.1.4.dist-info/METADATA
btrfs_simple_snapshots-0.1.4.dist-info/RECORD
btrfs_simple_snapshots-0.1.4.dist-info/WHEEL
btrfs_simple_snapshots-0.1.4.dist-info/entry_points.txt
btrfs_simple_snapshots-0.1.4.dist-info/metadata.json
btrfs_simple_snapshots-0.1.4.dist-info/top_level.txt
