Metadata-Version: 2.0
Name: btrfs-simple-snapshots
Version: 0.1.4
Summary: Snapshot you btrfs subvolumes and apply a retention policy
Home-page: https://github.com/ArnaudLevaufre/btrfs-simple-snapshots
Author: Arnaud Levaufre
Author-email: arnaud@levaufre.name
License: MIT
Keywords: btrfs snapshot subvolume backup
Platform: UNKNOWN
Classifier: Development Status :: 5 - Production/Stable
Classifier: Intended Audience :: System Administrators
Classifier: Intended Audience :: End Users/Desktop
Classifier: Topic :: System :: Filesystems
Classifier: Topic :: System :: Archiving :: Backup
Classifier: License :: OSI Approved :: MIT License
Classifier: Programming Language :: Python :: 3.7
